langchain_excel_loader/__init__.py
langchain_excel_loader/main.py
langchain_excel_loader-0.1.1.dist-info/METADATA
langchain_excel_loader-0.1.1.dist-info/WHEEL
langchain_excel_loader-0.1.1.dist-info/top_level.txt
langchain_excel_loader-0.1.1.dist-info/RECORD
