Metadata-Version: 2.1
Name: langchain-excel-loader
Version: 0.1.1
Requires-Dist: openpyxl (>=3.1.2)
Requires-Dist: langchain-core (>=0.3.1)
Requires-Dist: langchain-community (>=0.3.1)
